Metadata-Version: 2.1
Name: nonebot-plugin-simple-httpcat
Version: 0.0.1
Summary: 适用于nonebot2 v11、简单粗暴的httpcat插件 调用https://http.cat的图片
Home-page: https://github.com/XTxiaoting14332/nonebot-plugin-simple-httpcat
Author: NightWind
Author-email: 2125714976@qq.com
License: UNKNOWN
Platform: UNKNOWN
License-File: LICENSE
Requires-Dist: nonebot-adapter-onebot
Requires-Dist: nonebot2
